ersilia/__init__.py
ersilia/_static_version.py
ersilia/_version.py
ersilia/api/__init__.py
ersilia/api/commands/__init__.py
ersilia/api/commands/catalog.py
ersilia/api/commands/close.py
ersilia/api/commands/delete.py
ersilia/api/commands/example.py
ersilia/api/commands/fetch.py
ersilia/api/commands/info.py
ersilia/api/commands/is_fetched.py
ersilia/api/commands/run.py
ersilia/api/commands/serve.py
ersilia/api/create_api.py
ersilia/api/echo.py
ersilia/app/__init__.py
ersilia/app/fastapi/__init__.py
ersilia/app/streamlit/__init__.py
ersilia/auth/__init__.py
ersilia/auth/auth.py
ersilia/cli/__init__.py
ersilia/cli/cmd.py
ersilia/cli/commands/__init__.py
ersilia/cli/commands/catalog.py
ersilia/cli/commands/close.py
ersilia/cli/commands/delete.py
ersilia/cli/commands/dump.py
ersilia/cli/commands/example.py
ersilia/cli/commands/fetch.py
ersilia/cli/commands/info.py
ersilia/cli/commands/publish.py
ersilia/cli/commands/run.py
ersilia/cli/commands/serve.py
ersilia/cli/commands/test.py
ersilia/cli/commands/uninstall.py
ersilia/cli/commands/utils/__init__.py
ersilia/cli/create_cli.py
ersilia/cli/echo.py
ersilia/cli/messages.py
ersilia/core/__init__.py
ersilia/core/base.py
ersilia/core/model.py
ersilia/core/modelbase.py
ersilia/core/session.py
ersilia/core/tracking.py
ersilia/db/README.md
ersilia/db/__init__.py
ersilia/db/disk/__init__.py
ersilia/db/disk/fetched.py
ersilia/db/environments/__init__.py
ersilia/db/environments/localdb.py
ersilia/db/environments/managers.py
ersilia/db/hubdata/README.md
ersilia/db/hubdata/__init__.py
ersilia/db/hubdata/interfaces.py
ersilia/db/hubdata/localslugs.py
ersilia/db/hubdata/sanitize.py
ersilia/db/hubdata/tables.py
ersilia/default.py
ersilia/hub/__init__.py
ersilia/hub/bundle/__init__.py
ersilia/hub/bundle/bundle.py
ersilia/hub/bundle/repo.py
ersilia/hub/bundle/status.py
ersilia/hub/content/__init__.py
ersilia/hub/content/base_information.py
ersilia/hub/content/base_information_validator.py
ersilia/hub/content/card.py
ersilia-0.1.50.dist-info/METADATA
ersilia-0.1.50.dist-info/WHEEL
ersilia-0.1.50.dist-info/entry_points.txt
ersilia-0.1.50.dist-info/licenses/AUTHORSHIP.md
ersilia-0.1.50.dist-info/licenses/LICENSE
ersilia-0.1.50.dist-info/RECORD
