Metadata-Version: 2.4
Name: ersilia
Version: 0.1.50
Summary: A hub of AI/ML models for open source drug discovery and global health
License: GPLv3
License-File: AUTHORSHIP.md
License-File: LICENSE
Keywords: drug-discovery,machine-learning,ersilia,open-science,global-health,model-hub,infectious-diseases
Author: Ersilia Open Source Initiative
Author-email: hello@ersilia.io
Requires-Python: >=3.8
Classifier: License :: OSI Approved :: GNU General Public License v3 (GPLv3)
Classifier: License :: Other/Proprietary License
Classifier: Operating System :: OS Independent
Classifier: Programming Language :: Python :: 3
Classifier: Programming Language :: Python :: 3.8
Classifier: Programming Language :: Python :: 3.9
Classifier: Programming Language :: Python :: 3.10
Classifier: Programming Language :: Python :: 3.11
Classifier: Programming Language :: Python :: 3.12
Classifier: Programming Language :: Python :: 3.13
Classifier: Programming Language :: Python :: 3.14
Classifier: Topic :: Scientific/Engineering :: Artificial Intelligence
Provides-Extra: docs
Provides-Extra: test
Requires-Dist: PyYAML (>=6.0.1,<7.0.0)
Requires-Dist: aiofiles (<=24.1.0)
Requires-Dist: aiohttp (>=3.10.11)
Requires-Dist: boto3 (>=1.28.40,<2.0.0)
Requires-Dist: click (>=8.1.7,<9.0.0)
Requires-Dist: docker (>=7.1.0,<8.0.0)
Requires-Dist: dockerfile-parse (>=2.0.1,<3.0.0)
Requires-Dist: emoji (>=2.8.0,<3.0.0)
Requires-Dist: fuzzywuzzy (>=0.18.0,<0.19.0) ; extra == "test"
Requires-Dist: h5py (>=3.7.0,<4.0.0)
Requires-Dist: inputimeout (>=1.0.4,<2.0.0)
Requires-Dist: jinja2 (>=3.1.2,<4.0.0) ; extra == "docs"
Requires-Dist: loguru (>=0.7.0)
Requires-Dist: nest_asyncio (<=1.6.0)
Requires-Dist: nox ; extra == "test"
Requires-Dist: numpy (<=1.26.4)
Requires-Dist: pandas (>=2.0,<3.0)
Requires-Dist: pre-commit ; extra == "test"
Requires-Dist: psutil (>=5.9.0)
Requires-Dist: pytest (>=7.4.0,<8.0.0) ; extra == "test"
Requires-Dist: pytest-asyncio (<=0.24.0) ; extra == "test"
Requires-Dist: pytest-benchmark (<=4.0.0) ; extra == "test"
Requires-Dist: redis (>=5.1)
Requires-Dist: requests (>=2.31.0,<3.0.0)
Requires-Dist: rich ; extra == "test"
Requires-Dist: ruff ; extra == "test"
Requires-Dist: scipy ; extra == "test"
Requires-Dist: sphinx (>=6.0.0) ; extra == "docs"
Requires-Dist: tqdm (>=4.66.1,<5.0.0)
Requires-Dist: validators (>=0.21.0,<0.22.0) ; python_version >= "3.8"
Project-URL: Documentation, https://ersilia.io/model-hub
Project-URL: Homepage, https://ersilia.io
Project-URL: Repository, https://github.com/ersilia-os/ersilia
